fastappear/__init__.py
fastappear/main.py
fastappear/template/.dockerignore
fastappear/template/.env.example
fastappear/template/.gitignore
fastappear/template/Dockerfile
fastappear/template/README.md
fastappear/template/docker-compose.yaml
fastappear/template/gunicorn_conf.py
fastappear/template/mypy.ini
fastappear/template/pyproject.toml
fastappear/template/uv.lock
fastappear/template/.github/workflows/backend-qualityandtest-ci.yaml
fastappear/template/dev_docs/commands.md
fastappear/template/dev_docs/pythonic_guidelines.md
fastappear/template/scripts/generate_module.py
fastappear/template/scripts/generate_test_module.py
fastappear/template/src/__init__.py
fastappear/template/src/config.py
fastappear/template/src/main.py
fastappear/template/src/static_values/__init__.py
fastappear/template/src/utils/__init__.py
fastappear/template/src/utils/db.py
fastappear/template/src/utils/jwt.py
fastappear/template/src/utils/logger.py
fastappear/template/test/__init__.py
fastappear/template/test/test_config.py
fastappear/template/test/test_main.py
fastappear/template/test/static_values/__init__.py
fastappear/template/test/utils/__init__.py
fastappear/template/test/utils/test_db.py
fastappear/template/test/utils/test_jwt.py
fastappear/template/test/utils/test_logger.py
fastappear-0.2.6.dist-info/licenses/LICENSE
fastappear-0.2.6.dist-info/METADATA
fastappear-0.2.6.dist-info/WHEEL
fastappear-0.2.6.dist-info/entry_points.txt
fastappear-0.2.6.dist-info/top_level.txt
fastappear-0.2.6.dist-info/RECORD
