Metadata-Version: 2.4
Name: fastappear
Version: 0.2.6
Summary: Add your description here
Requires-Python: >=3.11
License-File: LICENSE
Requires-Dist: asyncpg>=0.30.0
Requires-Dist: fastapi[standard]>=0.121.2
Requires-Dist: gunicorn>=23.0.0
Requires-Dist: httpx>=0.28.1
Requires-Dist: passlib[bcrypt]>=1.7.4
Requires-Dist: pydantic[email]>=2.12.4
Requires-Dist: pydantic-settings>=2.12.0
Requires-Dist: pyjwt>=2.10.1
Requires-Dist: pytest>=9.0.1
Requires-Dist: pytest-asyncio>=1.3.0
Requires-Dist: pytest-cov>=7.0.0
Requires-Dist: python-dotenv>=1.2.1
Requires-Dist: python-multipart>=0.0.20
Requires-Dist: sqlalchemy>=2.0.44
Requires-Dist: sqlmodel>=0.0.27
Requires-Dist: uvicorn[standard]>=0.38.0
Requires-Dist: importlib>=1.0.4
Requires-Dist: aiosqlite>=0.21.0
Dynamic: license-file
